captionizer/__init__.py
captionizer/captionizer.py
captionizer/finder.py
captionizer/run_tests.py
captionizer-1.0.2.dist-info/LICENSE
captionizer-1.0.2.dist-info/METADATA
captionizer-1.0.2.dist-info/WHEEL
captionizer-1.0.2.dist-info/entry_points.txt
captionizer-1.0.2.dist-info/top_level.txt
captionizer-1.0.2.dist-info/RECORD
