Metadata-Version: 2.1
Name: captionizer
Version: 1.0.2
Summary: Creates captions from filenames and paths
Author-email: Fabio 'MrWHO' Torchetti <fabbari@gmail.com>
License: Apache License
Project-URL: Homepage, https://github.com/fabbarix/captionizer
Keywords: captions,images,stable diffusion
Classifier: License :: OSI Approved :: Apache Software License
Classifier: Programming Language :: Python
Classifier: Programming Language :: Python :: 3
Requires-Python: >=3.0
License-File: LICENSE
